git_editlog/__init__.py
git_editlog/__main__.py
git_editlog/pyinotify.py
git_editlog/pyinotify_watcher.py
git_editlog/repo_watcher.py
git_editlog/watchdog_watcher.py
git_editlog-1.0.1.dist-info/licenses/LICENSE
git_editlog-1.0.1.dist-info/METADATA
git_editlog-1.0.1.dist-info/WHEEL
git_editlog-1.0.1.dist-info/entry_points.txt
git_editlog-1.0.1.dist-info/top_level.txt
git_editlog-1.0.1.dist-info/RECORD
